<?xml version="1.0" encoding="UTF-8"?>
<MF0 version="1.1" packageUris="http://schema.mathworks.com/mf0/ci/19700101 http://schema.mathworks.com/mf0/sl_modelref_info/R2023a http://schema.mathworks.com/mf0/slexec_mm_sto/R2023a_202208151321 http://schema.mathworks.com/mf0/sltp_mm/R2023a_202209151115">
  <ModelRefInfoRepo.ModelRefInfoRoot type="ModelRefInfoRepo.ModelRefInfoRoot" uuid="202a99f6-c792-40ed-a510-54c48fea25f4">
    <JITEngines>sNhogm2KKhAI7YvCbioJryC</JITEngines>
    <childModelRefInfo type="ModelRefInfoRepo.ChildModelRefInfo" uuid="22a6b610-02bb-4cb7-a893-a2ad3e258a98">
      <modelName>CL_modelid</modelName>
      <modelPath>CL_modelid</modelPath>
    </childModelRefInfo>
    <clockResolutions type="ModelRefInfoRepo.ClockResolutionInfo" uuid="f53dbc03-bc9f-46f1-9548-e23a04912661">
      <rateIdx>1</rateIdx>
      <resolution>.001</resolution>
      <source>DeducedFromSampleTime</source>
    </clockResolutions>
    <dataTransferInfos>AAFJTQAAAAAOAAAAOAAAAAYAAAAIAAAAAgAAAAAAAAAFAAAACAAAAAAAAAABAAAAAQAAAAAAAAAFAAQAAQAAAAEAAAAAAAAA</dataTransferInfos>
    <defaultsCMapping>{&quot;Inports&quot;:&quot;{\&quot;Name\&quot;:\&quot;Default\&quot;,\&quot;Checksum\&quot;:\&quot;Default\&quot;,\&quot;PerInstancePropertiesChecksum\&quot;:\&quot;\&quot;,\&quot;MemorySectionName\&quot;:\&quot;\&quot;,\&quot;MemorySectionChecksum\&quot;:\&quot;\&quot;}&quot;,&quot;Outports&quot;:&quot;{\&quot;Name\&quot;:\&quot;Default\&quot;,\&quot;Checksum\&quot;:\&quot;Default\&quot;,\&quot;PerInstancePropertiesChecksum\&quot;:\&quot;\&quot;,\&quot;MemorySectionName\&quot;:\&quot;\&quot;,\&quot;MemorySectionChecksum\&quot;:\&quot;\&quot;}&quot;,&quot;ParameterArguments&quot;:&quot;{\&quot;Name\&quot;:\&quot;Default\&quot;,\&quot;Checksum\&quot;:\&quot;Default\&quot;,\&quot;PerInstancePropertiesChecksum\&quot;:\&quot;\&quot;,\&quot;MemorySectionName\&quot;:\&quot;None\&quot;,\&quot;MemorySectionChecksum\&quot;:\&quot;None\&quot;}&quot;,&quot;LocalParameters&quot;:&quot;{\&quot;Name\&quot;:\&quot;Default\&quot;,\&quot;Checksum\&quot;:\&quot;Default\&quot;,\&quot;PerInstancePropertiesChecksum\&quot;:\&quot;\&quot;,\&quot;MemorySectionName\&quot;:\&quot;\&quot;,\&quot;MemorySectionChecksum\&quot;:\&quot;\&quot;}&quot;,&quot;GlobalParameters&quot;:&quot;{\&quot;Name\&quot;:\&quot;Default\&quot;,\&quot;Checksum\&quot;:\&quot;Default\&quot;,\&quot;PerInstancePropertiesChecksum\&quot;:\&quot;\&quot;,\&quot;MemorySectionName\&quot;:\&quot;\&quot;,\&quot;MemorySectionChecksum\&quot;:\&quot;\&quot;}&quot;,&quot;InternalData&quot;:&quot;{\&quot;Name\&quot;:\&quot;Default\&quot;,\&quot;Checksum\&quot;:\&quot;Default\&quot;,\&quot;PerInstancePropertiesChecksum\&quot;:\&quot;\&quot;,\&quot;MemorySectionName\&quot;:\&quot;\&quot;,\&quot;MemorySectionChecksum\&quot;:\&quot;\&quot;}&quot;,&quot;SharedLocalDataStores&quot;:&quot;{\&quot;Name\&quot;:\&quot;Default\&quot;,\&quot;Checksum\&quot;:\&quot;Default\&quot;,\&quot;PerInstancePropertiesChecksum\&quot;:\&quot;\&quot;,\&quot;MemorySectionName\&quot;:\&quot;None\&quot;,\&quot;MemorySectionChecksum\&quot;:\&quot;None\&quot;}&quot;,&quot;GlobalDataStores&quot;:&quot;{\&quot;Name\&quot;:\&quot;Default\&quot;,\&quot;Checksum\&quot;:\&quot;Default\&quot;,\&quot;PerInstancePropertiesChecksum\&quot;:\&quot;\&quot;,\&quot;MemorySectionName\&quot;:\&quot;None\&quot;,\&quot;MemorySectionChecksum\&quot;:\&quot;None\&quot;}&quot;,&quot;Constants&quot;:&quot;{\&quot;Name\&quot;:\&quot;Default\&quot;,\&quot;Checksum\&quot;:\&quot;Default\&quot;,\&quot;PerInstancePropertiesChecksum\&quot;:\&quot;\&quot;,\&quot;MemorySectionName\&quot;:\&quot;\&quot;,\&quot;MemorySectionChecksum\&quot;:\&quot;\&quot;}&quot;,&quot;DataTransfers&quot;:&quot;{\&quot;Name\&quot;:\&quot;Default\&quot;,\&quot;Checksum\&quot;:\&quot;Default\&quot;,\&quot;PerInstancePropertiesChecksum\&quot;:\&quot;\&quot;,\&quot;MemorySectionName\&quot;:\&quot;None\&quot;,\&quot;MemorySectionChecksum\&quot;:\&quot;None\&quot;}&quot;,&quot;ModelData&quot;:&quot;{\&quot;Name\&quot;:\&quot;Default\&quot;,\&quot;Checksum\&quot;:\&quot;Default\&quot;,\&quot;PerInstancePropertiesChecksum\&quot;:\&quot;\&quot;,\&quot;MemorySectionName\&quot;:\&quot;None\&quot;,\&quot;MemorySectionChecksum\&quot;:\&quot;None\&quot;}&quot;,&quot;InitializeTerminate&quot;:&quot;{\&quot;Name\&quot;:\&quot;Default\&quot;,\&quot;Checksum\&quot;:\&quot;Default\&quot;,\&quot;PerInstancePropertiesChecksum\&quot;:\&quot;\&quot;,\&quot;MemorySectionName\&quot;:\&quot;\&quot;,\&quot;MemorySectionChecksum\&quot;:\&quot;\&quot;}&quot;,&quot;Execution&quot;:&quot;{\&quot;Name\&quot;:\&quot;Default\&quot;,\&quot;Checksum\&quot;:\&quot;Default\&quot;,\&quot;PerInstancePropertiesChecksum\&quot;:\&quot;\&quot;,\&quot;MemorySectionName\&quot;:\&quot;\&quot;,\&quot;MemorySectionChecksum\&quot;:\&quot;\&quot;}&quot;,&quot;SharedUtility&quot;:&quot;{\&quot;Name\&quot;:\&quot;Default\&quot;,\&quot;Checksum\&quot;:\&quot;Default\&quot;,\&quot;PerInstancePropertiesChecksum\&quot;:\&quot;\&quot;,\&quot;MemorySectionName\&quot;:\&quot;\&quot;,\&quot;MemorySectionChecksum\&quot;:\&quot;\&quot;}&quot;}</defaultsCMapping>
    <fastestNoncontSigFeedingDerivPorts>-1.0</fastestNoncontSigFeedingDerivPorts>
    <globalVariables>K</globalVariables>
    <globalVariables>amp</globalVariables>
    <globalVariables>omega</globalVariables>
    <globalVariables>sys_d</globalVariables>
    <hasBlockWithPeriodicDiscreteSampleTime>true</hasBlockWithPeriodicDiscreteSampleTime>
    <hasBwsAccessed>true</hasBwsAccessed>
    <hasBwsAccessedByAnyModel>true</hasBwsAccessedByAnyModel>
    <hasContinuousSampleTime>true</hasContinuousSampleTime>
    <isBdInSimModeForSimCodegenVariants>false</isBdInSimModeForSimCodegenVariants>
    <loggingSaveFormat>2</loggingSaveFormat>
    <maxFreqHz>-1.0</maxFreqHz>
    <needAbsoluteTimeDisallowInitPort>true</needAbsoluteTimeDisallowInitPort>
    <nonTunableVariables>omega</nonTunableVariables>
    <numDStateRecs>1</numDStateRecs>
    <numDataInputPorts>0</numDataInputPorts>
    <numLoggableDStateRecs>1</numLoggableDStateRecs>
    <numLoggableJacobianDStates>6</numLoggableJacobianDStates>
    <runtimeNonFcnCallRateInfos type="ModelRefInfoRepo.RateInfo">
      <compiled>true</compiled>
      <needAbsoluteTime>true</needAbsoluteTime>
      <period>0.0</period>
      <priority>40</priority>
      <rateIdx>0</rateIdx>
    </runtimeNonFcnCallRateInfos>
    <runtimeNonFcnCallRateInfos type="ModelRefInfoRepo.RateInfo">
      <compiled>true</compiled>
      <needAbsoluteTime>true</needAbsoluteTime>
      <nonFcnCallPartitionName>Cont</nonFcnCallPartitionName>
      <period>.001</period>
      <priority>40</priority>
      <rateIdx>1</rateIdx>
    </runtimeNonFcnCallRateInfos>
    <sampleTimeInheritanceRule>2</sampleTimeInheritanceRule>
    <solverStatusFlags>323</solverStatusFlags>
    <timingAndTaskingRegistry>&lt;?xml version=&quot;1.0&quot;?&gt;
&lt;slexec_sto version=&quot;1.1&quot; packageUris=&quot;http://schema.mathworks.com/mf0/slexec_mm_sto/R2023a_202208151321&quot;&gt;
  &lt;sto.Registry type=&quot;sto.Registry&quot; uuid=&quot;f294c5c6-8aed-47b3-be91-09742ac469ca&quot;&gt;
    &lt;executionSpec&gt;Undetermined&lt;/executionSpec&gt;
    &lt;identifier&gt;CL_modelid&lt;/identifier&gt;
    &lt;clockRegistry type=&quot;sto.ClockRegistry&quot; uuid=&quot;9452d875-6feb-4bc0-8965-5928be0483ce&quot;&gt;
      &lt;clocks type=&quot;sto.Timer&quot; uuid=&quot;3902facb-f9a5-43ac-b8b8-a1cdd31245d6&quot;&gt;
        &lt;clockTickConstraint&gt;PeriodicWithFixedResolution&lt;/clockTickConstraint&gt;
        &lt;computedFundamentalDiscretePeriod&gt;.001&lt;/computedFundamentalDiscretePeriod&gt;
        &lt;fastestDiscreteRate type=&quot;sto.ClassicPeriodicDiscreteRate&quot; uuid=&quot;1f7ed3e1-2707-48a4-872b-ad0f3a7926b2&quot;/&gt;
        &lt;isDefaultTimer&gt;true&lt;/isDefaultTimer&gt;
        &lt;resolution&gt;.001&lt;/resolution&gt;
        &lt;timeAdvanceMode&gt;FixedStep&lt;/timeAdvanceMode&gt;
        &lt;identifier&gt;CL_modelid::defaultTimer&lt;/identifier&gt;
        &lt;rates type=&quot;sto.ContinuousRate&quot; uuid=&quot;2acad083-c1b3-44a3-a918-81bbcf7fa2f8&quot;&gt;
          &lt;annotation&gt;Cont&lt;/annotation&gt;
          &lt;clockId&gt;CL_modelid::defaultTimer&lt;/clockId&gt;
          &lt;description&gt;Continuous&lt;/description&gt;
          &lt;taskId&gt;_task0&lt;/taskId&gt;
          &lt;rateSpec type=&quot;sto.RateSpec&quot; uuid=&quot;39582129-dd33-47ef-80d9-ba60d456c21e&quot;/&gt;
        &lt;/rates&gt;
        &lt;rates type=&quot;sto.ClassicPeriodicDiscreteRate&quot; uuid=&quot;1f7ed3e1-2707-48a4-872b-ad0f3a7926b2&quot;&gt;
          &lt;annotation&gt;D1&lt;/annotation&gt;
          &lt;clockId&gt;CL_modelid::defaultTimer&lt;/clockId&gt;
          &lt;colorIndex&gt;2&lt;/colorIndex&gt;
          &lt;description&gt;Discrete 1&lt;/description&gt;
          &lt;rateIdx&gt;1&lt;/rateIdx&gt;
          &lt;taskId&gt;_task0&lt;/taskId&gt;
          &lt;rateSpec type=&quot;sto.RateSpec&quot; uuid=&quot;975d9d9f-0d42-499c-9871-0b6f478a1cb4&quot;&gt;
            &lt;period&gt;.001&lt;/period&gt;
            &lt;rateType&gt;ClassicPeriodicDiscrete&lt;/rateType&gt;
          &lt;/rateSpec&gt;
        &lt;/rates&gt;
        &lt;baseRate type=&quot;sto.ContinuousRate&quot; uuid=&quot;e039ab74-dcc6-4ab3-b4b9-35d76bacbb35&quot;&gt;
          &lt;annotation&gt;Cont&lt;/annotation&gt;
          &lt;clockId&gt;CL_modelid::defaultTimer&lt;/clockId&gt;
          &lt;description&gt;Continuous&lt;/description&gt;
          &lt;taskId&gt;_task0&lt;/taskId&gt;
          &lt;rateSpec type=&quot;sto.RateSpec&quot; uuid=&quot;aedfcffe-0928-4383-ba74-84fda2c842cf&quot;/&gt;
        &lt;/baseRate&gt;
      &lt;/clocks&gt;
      &lt;clocks type=&quot;sto.Event&quot; uuid=&quot;8d21e8b2-b7c7-474e-99cb-a231d62c588c&quot;&gt;
        &lt;eventType&gt;PARAMETER_CHANGE_EVENT&lt;/eventType&gt;
        &lt;cNum&gt;1&lt;/cNum&gt;
        &lt;clockType&gt;Event&lt;/clockType&gt;
        &lt;identifier&gt;ParameterChangeEvent&lt;/identifier&gt;
        &lt;rates type=&quot;sto.ModelWideEventRate&quot; uuid=&quot;cc94647c-dc55-45bd-b405-16d86ba1ebd2&quot;&gt;
          &lt;clockId&gt;ParameterChangeEvent&lt;/clockId&gt;
          &lt;rateIdx&gt;-1&lt;/rateIdx&gt;
          &lt;taskId&gt;ModelWideParameterChangeEvent&lt;/taskId&gt;
          &lt;useForExecution&gt;NotForExecution&lt;/useForExecution&gt;
          &lt;rateSpec type=&quot;sto.RateSpec&quot; uuid=&quot;ae8ca861-a9a3-47f3-8808-1bf6a6b87256&quot;&gt;
            &lt;period&gt;inf&lt;/period&gt;
            &lt;rateType&gt;ModelWideParameterChangeEvent&lt;/rateType&gt;
          &lt;/rateSpec&gt;
        &lt;/rates&gt;
      &lt;/clocks&gt;
      &lt;timeAdvanceMode&gt;FixedStep&lt;/timeAdvanceMode&gt;
    &lt;/clockRegistry&gt;
    &lt;taskRegistry type=&quot;sto.TaskRegistry&quot; uuid=&quot;a811e9a3-7f28-43ce-8f43-594494bc4ed1&quot;&gt;
      &lt;rootTaskHierarchyElements type=&quot;sto.Task&quot; uuid=&quot;0a90f614-fa60-4052-9a61-53d1f51ee0de&quot;&gt;
        &lt;isExplicit&gt;true&lt;/isExplicit&gt;
        &lt;rates type=&quot;sto.ModelWideEventRate&quot; uuid=&quot;2b461b57-f9d7-4e0a-9fe6-1274530283ae&quot;&gt;
          &lt;clockId&gt;ParameterChangeEvent&lt;/clockId&gt;
          &lt;rateIdx&gt;-1&lt;/rateIdx&gt;
          &lt;taskId&gt;ModelWideParameterChangeEvent&lt;/taskId&gt;
          &lt;useForExecution&gt;NotForExecution&lt;/useForExecution&gt;
          &lt;rateSpec type=&quot;sto.RateSpec&quot; uuid=&quot;f0d62bb7-4050-4ae2-b528-ad7471c458f7&quot;&gt;
            &lt;period&gt;inf&lt;/period&gt;
            &lt;rateType&gt;ModelWideParameterChangeEvent&lt;/rateType&gt;
          &lt;/rateSpec&gt;
        &lt;/rates&gt;
        &lt;schedulingClockId&gt;ParameterChangeEvent&lt;/schedulingClockId&gt;
        &lt;timeKeeperClockId&gt;CL_modelid::defaultTimer&lt;/timeKeeperClockId&gt;
        &lt;elementType&gt;Task&lt;/elementType&gt;
        &lt;identifier&gt;ModelWideParameterChangeEvent&lt;/identifier&gt;
        &lt;priority&gt;-1&lt;/priority&gt;
      &lt;/rootTaskHierarchyElements&gt;
      &lt;rootTaskHierarchyElements type=&quot;sto.Task&quot; uuid=&quot;b54aa01b-d216-44a2-8056-ac6f5548d37e&quot;&gt;
        &lt;isExecutable&gt;true&lt;/isExecutable&gt;
        &lt;orderIndex&gt;1&lt;/orderIndex&gt;
        &lt;rates type=&quot;sto.ContinuousRate&quot; uuid=&quot;455aa3a6-5524-45cf-9e71-36d2a6626843&quot;&gt;
          &lt;annotation&gt;Cont&lt;/annotation&gt;
          &lt;clockId&gt;CL_modelid::defaultTimer&lt;/clockId&gt;
          &lt;description&gt;Continuous&lt;/description&gt;
          &lt;taskId&gt;_task0&lt;/taskId&gt;
          &lt;rateSpec type=&quot;sto.RateSpec&quot; uuid=&quot;21631e90-136a-4ac6-bff8-a2a04312bc07&quot;/&gt;
        &lt;/rates&gt;
        &lt;rates type=&quot;sto.ClassicPeriodicDiscreteRate&quot; uuid=&quot;d2380b78-27eb-4955-9b8d-88719489c2c3&quot;&gt;
          &lt;annotation&gt;D1&lt;/annotation&gt;
          &lt;clockId&gt;CL_modelid::defaultTimer&lt;/clockId&gt;
          &lt;colorIndex&gt;2&lt;/colorIndex&gt;
          &lt;description&gt;Discrete 1&lt;/description&gt;
          &lt;rateIdx&gt;1&lt;/rateIdx&gt;
          &lt;taskId&gt;_task0&lt;/taskId&gt;
          &lt;rateSpec type=&quot;sto.RateSpec&quot; uuid=&quot;3b4ef92b-028c-4db7-b810-724ccf71dcba&quot;&gt;
            &lt;period&gt;.001&lt;/period&gt;
            &lt;rateType&gt;ClassicPeriodicDiscrete&lt;/rateType&gt;
          &lt;/rateSpec&gt;
        &lt;/rates&gt;
        &lt;schedulingClockId&gt;CL_modelid::defaultTimer&lt;/schedulingClockId&gt;
        &lt;timeKeeperClockId&gt;CL_modelid::defaultTimer&lt;/timeKeeperClockId&gt;
        &lt;elementType&gt;Task&lt;/elementType&gt;
        &lt;identifier&gt;_task0&lt;/identifier&gt;
        &lt;priority&gt;40&lt;/priority&gt;
      &lt;/rootTaskHierarchyElements&gt;
      &lt;taskDependencyGraph type=&quot;sto.SerializedTaskConnectionList&quot; uuid=&quot;2f87f382-88fa-4c58-aa2c-d1505dfebd8f&quot;&gt;
        &lt;clockIdentifier&gt;CL_modelid::defaultTimer&lt;/clockIdentifier&gt;
        &lt;taskIdentifier&gt;_task0&lt;/taskIdentifier&gt;
      &lt;/taskDependencyGraph&gt;
      &lt;taskDependencyGraph type=&quot;sto.SerializedTaskConnectionList&quot; uuid=&quot;b6e762fe-a556-4c1c-a7e3-4ac3bb8339cd&quot;&gt;
        &lt;clockIdentifier&gt;ParameterChangeEvent&lt;/clockIdentifier&gt;
        &lt;taskIdentifier&gt;ModelWideParameterChangeEvent&lt;/taskIdentifier&gt;
      &lt;/taskDependencyGraph&gt;
      &lt;taskingMode&gt;ClassicMultiTasking&lt;/taskingMode&gt;
    &lt;/taskRegistry&gt;
  &lt;/sto.Registry&gt;
&lt;/slexec_sto&gt;</timingAndTaskingRegistry>
    <FMUBlockMap type="ModelRefInfoRepo.FMUBlockInfo" uuid="0274c06d-5cbc-498b-ade6-850939d8063f"/>
    <codeGenInfo type="ModelRefInfoRepo.CodeGenInformation" uuid="ad1ade06-456f-467f-b831-33045f133672"/>
    <compiledVariantInfos type="ModelRefInfoRepo.CompiledVariantInfoMap" uuid="bf11d222-62ef-426d-b08d-76b6bd521013"/>
    <configSettingsForConsistencyChecks type="ModelRefInfoRepo.ConfigSettingsForConsistencyChecks" uuid="4c845130-f242-450f-8bde-6ca881dea912">
      <consistentOutportInitialization>true</consistentOutportInitialization>
      <fixedStepSize>.001</fixedStepSize>
      <frameDiagnosticSetting>2</frameDiagnosticSetting>
      <hasHybridSampleTime>true</hasHybridSampleTime>
      <signalLoggingSaveFormat>2</signalLoggingSaveFormat>
      <simSIMDOptimization>1</simSIMDOptimization>
      <solverName>FixedStepDiscrete</solverName>
      <solverType>SOLVER_TYPE_FIXEDSTEP</solverType>
      <hardwareSettings type="ModelRefInfoRepo.HardwareSettings" uuid="0d31d9ed-5b0b-4aa4-b7d6-6fc35a669983">
        <prodBitPerChar>8</prodBitPerChar>
        <prodBitPerDouble>64</prodBitPerDouble>
        <prodBitPerFloat>32</prodBitPerFloat>
        <prodBitPerInt>32</prodBitPerInt>
        <prodBitPerLong>32</prodBitPerLong>
        <prodBitPerLongLong>64</prodBitPerLongLong>
        <prodBitPerPointer>64</prodBitPerPointer>
        <prodBitPerPtrDiffT>64</prodBitPerPtrDiffT>
        <prodBitPerShort>16</prodBitPerShort>
        <prodBitPerSizeT>64</prodBitPerSizeT>
        <prodEndianess>1</prodEndianess>
        <prodShiftRight>true</prodShiftRight>
        <prodWordSize>64</prodWordSize>
      </hardwareSettings>
    </configSettingsForConsistencyChecks>
    <controllableInputRatesMap type="ModelRefInfoRepo.VarTsUIDMap" uuid="edff6900-d5b6-40ec-9a5f-4dd5e6b2f058"/>
    <controllableOutputRatesMap type="ModelRefInfoRepo.VarTsUIDMap" uuid="e3ab16cf-088e-4cee-865c-cfb6b0fb93b7"/>
    <dataPortGroup type="ModelRefInfoRepo.DataPortGroup" uuid="3f013dc2-8c44-4430-947c-efc6dc9041bc"/>
    <expFcnUnconnectedDataPortGroup type="ModelRefInfoRepo.DataPortGroup" uuid="479285a3-2aa0-4099-b417-6c0c9d7a151c"/>
    <interfaceParameterInfo type="ModelRefInfoRepo.InterfaceParameterInfo" uuid="c726ffac-4391-4ae5-b90b-6bc891c0b11e">
      <globalVariables type="ModelRefInfoRepo.BuiltinParameter" uuid="51e8acb6-f538-4e35-a452-0b5b60eb3a48">
        <dimensions>1</dimensions>
        <dimensions>6</dimensions>
        <isUsed>true</isUsed>
        <numDimensions>2</numDimensions>
        <parameterName>K</parameterName>
      </globalVariables>
      <globalVariables type="ModelRefInfoRepo.BuiltinParameter" uuid="574f6d2d-2a88-413f-bc1c-a09986fec1c8">
        <dimensions>1</dimensions>
        <dimensions>1</dimensions>
        <isUsed>true</isUsed>
        <numDimensions>2</numDimensions>
        <parameterName>amp</parameterName>
      </globalVariables>
      <globalVariables type="ModelRefInfoRepo.BuiltinParameter" uuid="6ea4f17c-747c-4746-81ec-ac4c2a5556ed">
        <dimensions>1</dimensions>
        <dimensions>1</dimensions>
        <isUsed>true</isUsed>
        <numDimensions>2</numDimensions>
        <parameterName>omega</parameterName>
      </globalVariables>
    </interfaceParameterInfo>
    <messageInfo type="ModelRefInfoRepo.MessageInformation" uuid="42e8bfd8-2bef-495e-b5cc-a0ade06f5cb4"/>
    <methodInfo type="ModelRefInfoRepo.MethodExistenceInfo" uuid="6228b4f3-8b96-4b57-aaca-2187e4b9f31c">
      <hasDisableMethod>true</hasDisableMethod>
      <hasEnableMethod>true</hasEnableMethod>
      <hasSystemInitializeMethod>true</hasSystemInitializeMethod>
      <hasSystemResetMethod>true</hasSystemResetMethod>
      <hasTerminateMethod>true</hasTerminateMethod>
      <hasUpdateMethod>true</hasUpdateMethod>
    </methodInfo>
    <periodicEventPortUnsupportedBlockInfo type="ModelRefInfoRepo.PeriodicEventPortUnsupportedBlockInfo" uuid="3eefbfd9-1f71-414a-a607-e9cddd75489a"/>
    <portGroupsRequireSameRate type="ModelRefInfoRepo.PortGroupsRequireSameRate" uuid="f6052e16-6c46-4572-afdc-eff18e7cab6e">
      <DSMPortGroups type="ModelRefInfoRepo.NameToPortGroupIdxVectMap" uuid="333ed8d1-8d69-4cce-929c-edde8797f3b1"/>
      <GlobalDSMPortGroups type="ModelRefInfoRepo.NameToPortGroupIdxVectMap" uuid="62f33d27-38a6-4c5d-a775-5856b01996e8"/>
      <mergedPortGroups type="ModelRefInfoRepo.NameToPortGroupIdxVectMap" uuid="c7238afa-c5bd-4475-b2f5-91542cd5e8ca"/>
    </portGroupsRequireSameRate>
    <rateBasedMdlGlobalDSMRateSpec type="ModelRefInfoRepo.GlobalDSMRateSpecMap" uuid="f9680e81-3dc9-41e2-ab64-e33cecc88fda"/>
    <rateSpecOfGlobalDSMAccessedByDescExpFcnMdlMap type="ModelRefInfoRepo.GlobalDSMRateSpecMap" uuid="8e27db4f-6e14-4084-bff9-995651bc0ab6"/>
    <rootBlockDiagramInterface type="ci.Model" uuid="d338f1ff-7531-46d3-92de-b896970c4843">
      <p_RootComponentInterface type="ci.ComponentInterface" uuid="8978d788-25f9-4bc3-999a-a05b9a9928ed">
        <p_Name>CL_modelid</p_Name>
        <p_Type>ROOT</p_Type>
      </p_RootComponentInterface>
    </rootBlockDiagramInterface>
    <simulinkFunctions type="ModelRefInfoRepo.SimulinkFunctions" uuid="a20bd7d2-1aa7-42b6-ba26-9ec0d701d576">
      <compSimulinkFunctionCatalog></compSimulinkFunctionCatalog>
    </simulinkFunctions>
    <sltpContext type="sltp.mm.core.Context" uuid="eaa72d88-4ee5-416d-b060-e92534399baf">
      <unusedTaskIds>1</unusedTaskIds>
      <defaultEventBehavior type="sltp.mm.core.EventBehavior" uuid="d7ab87b1-5e71-4ca0-9d82-f03c5bd9acc2"/>
      <editorState type="sltp.mm.core.EditorState" uuid="dfddbac0-357d-476b-aee8-f6ce847b5b79">
        <isSynchronized>true</isSynchronized>
        <panelState type="sltp.mm.core.EditorPanelState" uuid="ce5f0e47-f930-4581-a1d3-2284783b58ef"/>
      </editorState>
      <rootTask type="sltp.mm.core.Task" uuid="d68bf30b-f682-4bfc-92a1-8148c2d0e839">
        <context type="sltp.mm.core.Context" uuid="eaa72d88-4ee5-416d-b060-e92534399baf"/>
        <explicit>false</explicit>
        <name>Default</name>
        <priority>-2147483648</priority>
        <subgraph type="sltp.mm.core.Graph" uuid="d49cbe55-bd86-4672-a486-46c034e89138">
          <tasks type="sltp.mm.core.Task" uuid="944b15bd-f7ca-4b4c-bbc0-055e4ce4bb9b">
            <baseTask>true</baseTask>
            <context type="sltp.mm.core.Context" uuid="eaa72d88-4ee5-416d-b060-e92534399baf"/>
            <explicit>false</explicit>
            <id>2</id>
            <isTimed>true</isTimed>
            <name>Cont</name>
            <priority>40</priority>
            <rates type="sltp.mm.core.Rate" uuid="98954908-daa2-48b5-b3eb-4c2b1175c63c">
              <annotation>Cont</annotation>
              <color>255</color>
              <hasBlocks>true</hasBlocks>
              <identifier>Continuous00</identifier>
              <rateIndex>0</rateIndex>
              <rateSpec type="sltp.mm.core.RateSpec">
                <period>0.0</period>
              </rateSpec>
              <sti>0</sti>
            </rates>
            <rates type="sltp.mm.core.Rate" uuid="2d2ede48-c8ef-4f52-b9e4-f61f9c14a237">
              <annotation>D1</annotation>
              <color>-436207361</color>
              <hasBlocks>true</hasBlocks>
              <rateIndex>1</rateIndex>
              <rateSpec type="sltp.mm.core.RateSpec">
                <period>.001</period>
              </rateSpec>
              <sti>1</sti>
            </rates>
          </tasks>
        </subgraph>
      </rootTask>
    </sltpContext>
    <stateWriterToOwnerMap type="ModelRefInfoRepo.StateWriterInfo" uuid="4d15481f-0cc2-4d36-bdf0-249d03e567dd"/>
    <stoClientDataRegistry type="sto.ClientDataRegistry" uuid="835651e2-8e62-4b61-abbc-1019ba70537d">
      <dataSets type="sto.ClientClockNamedDataSet" uuid="ab8d319e-b2ed-4a27-876a-2f95320272e7">
        <tag>sltpEvents</tag>
      </dataSets>
      <dataSets type="sto.ClientTaskHierarchyElementNamedDataSet" uuid="f2c0eec4-5108-43c7-9a6b-ba6f66049199">
        <tag>sltpTaskGroups</tag>
      </dataSets>
      <dataSets type="sto.ClientTaskHierarchyElementNamedDataSet" uuid="14ddb7fe-49eb-4bc5-8fc5-10e4ea2e6117">
        <dSet type="ModelRefInfoRepo.SltpTaskData" uuid="b81f34b4-7e2e-47f0-b7bd-42b271b67bdb"/>
        <tSet type="ModelRefInfoRepo.SltpTaskData" uuid="b81f34b4-7e2e-47f0-b7bd-42b271b67bdb">
          <dataName>Cont</dataName>
          <linkedSet type="sto.ClientTaskHierarchyElementNamedDataSet" uuid="14ddb7fe-49eb-4bc5-8fc5-10e4ea2e6117"/>
          <id type="sto.TaskHierarchyElementId">
            <clockId>CL_modelid::defaultTimer</clockId>
            <id>_task0</id>
          </id>
        </tSet>
        <tag>sltpTasks</tag>
      </dataSets>
    </stoClientDataRegistry>
    <varTsUIDMap type="ModelRefInfoRepo.VarTsUIDMap" uuid="d5e4b331-05c0-4781-acaa-b901cca9868d"/>
  </ModelRefInfoRepo.ModelRefInfoRoot>
</MF0>